package/__init__.py
package/main.py
thisisjustapackage-0.0.6.dist-info/LICENSE
thisisjustapackage-0.0.6.dist-info/METADATA
thisisjustapackage-0.0.6.dist-info/WHEEL
thisisjustapackage-0.0.6.dist-info/top_level.txt
thisisjustapackage-0.0.6.dist-info/RECORD
